waterpybal/.gitattributes
waterpybal/README.md
waterpybal/__init__.py
waterpybal/balance_calcs.py
waterpybal/dataset_prep.py
waterpybal/inf_calcs.py
waterpybal/pet_calcs.py
waterpybal/post_processing.py
waterpybal/requirements.txt
waterpybal/swr_calcs.py
waterpybal/urban_cycle.py
waterpybal/version.py
waterpybal-1.0.0.dist-info/LICENSE
waterpybal-1.0.0.dist-info/WHEEL
waterpybal-1.0.0.dist-info/METADATA
waterpybal-1.0.0.dist-info/RECORD
