Metadata-Version: 2.1
Name: waterpybal
Version: 1.0.0
Summary: An open source library for water balance modelling 
Author-email: IDAEA-CSIC / Ashkan Hassanzadeh <ashkan.hassanzadeh@gmail.com>
Requires-Python: >=3.3
Classifier: License :: OSI Approved :: GNU Affero General Public License v3 or later (AGPLv3+)
Classifier: Programming Language :: Python :: 3
Classifier: Development Status :: 4 - Beta
Requires-Dist: GDAL
Requires-Dist: matplotlib
Requires-Dist: netCDF4
Requires-Dist: numpy
Requires-Dist: osgeo
Requires-Dist: pandas
Requires-Dist: pyet
Requires-Dist: rasterio
Requires-Dist: richdem
Requires-Dist: rioxarray
Requires-Dist: xarray
Project-URL: home-page, https://github.com/IDAEA-EVS/waterpybal
